Metadata-Version: 2.1
Name: gbinomial-probability
Version: 1.0
Summary: Gaussian and Binomial Distributions
Author: Seah Mei Yin
Author-email: tiffanyseah94@gmail.com
